AUTHORS.rst
CONTRIBUTING.rst
HISTORY.rst
LICENSE
MANIFEST.in
README.md
README.rst
setup.cfg
setup.py
docs/2by2.png
docs/Makefile
docs/authors.rst
docs/conf.py
docs/contributing.rst
docs/history.rst
docs/index.rst
docs/installation.rst
docs/make.bat
docs/readme.rst
docs/usage.rst
docs/_build/html/_static/background_b01.png
docs/_build/html/_static/file.png
docs/_build/html/_static/minus.png
docs/_build/html/_static/plus.png
tests/__init__.py
tests/test_tprojection.py
tests/test_utils.py
tprojection/__init__.py
tprojection/core.py
tprojection/datasets.py
tprojection/titanic.csv
tprojection/utils.py
tprojection.egg-info/PKG-INFO
tprojection.egg-info/SOURCES.txt
tprojection.egg-info/dependency_links.txt
tprojection.egg-info/not-zip-safe
tprojection.egg-info/requires.txt
tprojection.egg-info/top_level.txt