Metadata-Version: 1.2
Name: tprojection
Version: 0.2.4
Summary: Visualize the relation between a dependent variable and a predictor in a meaningful way
Home-page: https://github.com/greghor/tprojection
Author: Gregoire Hornung
Author-email: greghor4@gmail.com
License: MIT license
Keywords: tprojection
Platform: UNKNOWN
Classifier: Development Status :: 2 - Pre-Alpha
Classifier: Intended Audience :: Developers
Classifier: License :: OSI Approved :: MIT License
Classifier: Natural Language :: English
Classifier: Programming Language :: Python :: 3
Classifier: Programming Language :: Python :: 3.5
Classifier: Programming Language :: Python :: 3.6
Classifier: Programming Language :: Python :: 3.7
Classifier: Programming Language :: Python :: 3.8
Requires-Python: >=3.5
